[
    { "id": 0,
      "animation": "card",
      "description": "",
      "img": "../beforediningedit.jpeg",
      "afterimg": "../afterdiningedit.jpeg",
      "type": "From 1850's to modern elegance",
      "descript": "This kitchen table and chair set went thru a rigourous sand, finish and sealing to give it a whole new look"
    },
    { "id": 1,
      "animation": "card",
      "description": "",
      "img": "../beforedresser.jpeg",
      "afterimg": "../afterdresseredit.jpeg",
      "type": "Before"
     },
    { "id": 2,
      "animation": "card",
      "description": "",
      "img": "../beforetable.jpeg",
      "afterimg": "../aftertabledit.jpeg",
      "type": "Before"
     },
     { "id": 3,
      "animation": "card",
      "description": "",
      "img": "../beforeshutteredit.jpeg",
      "afterimg": "../aftershutteredit.jpeg",
      "type": "Before" 
    },
    { "id": 4,
      "animation": "card",
      "description": "",
      "img": "../beforestooledit.jpeg",
      "afterimg": "../afterstooledit.jpeg",
      "type": "Before"
     }
  ]